gugik_api/__init__.py
gugik_api/gugik_api.py
gugik_api/ll_convert.py
notebooks/__init__.py
tests/__init__.py
tests/test_gugik_api.py
gugik_api-0.1.dist-info/METADATA
gugik_api-0.1.dist-info/WHEEL
gugik_api-0.1.dist-info/top_level.txt
gugik_api-0.1.dist-info/RECORD
