Metadata-Version: 2.1
Name: gugik_api
Version: 0.1
Summary: A Python client for the GUGiK API
Home-page: https://github.com/lechplace/gugik_api
Author: Lech Hubicki
Author-email: lech.hubicki@gmail.com
Classifier: Programming Language :: Python :: 3
Classifier: License :: OSI Approved :: MIT License
Classifier: Operating System :: OS Independent
Requires-Python: >=3.8
Requires-Dist: requests >=2.0
Requires-Dist: pytest >=6.0
Requires-Dist: pyproj
Provides-Extra: dev
Requires-Dist: flake8 >=3.8 ; extra == 'dev'
